{
  "kpis": {
    "n_corpus_txs": 23876,
    "n_decoded_txs": 16890,
    "n_ilp_failed": 6986,
    "n_slots": 129301,
    "n_clusters": 74471,
    "n_singletons": 50126,
    "n_nontrivial": 24345,
    "largest_cluster": 91,
    "n_same_cj_collisions": 0,
    "n_analysed": 16890,
    "mean_n_eq": 7.655,
    "mean_certified": 4.688,
    "mean_residual": 2.968,
    "share_any_reduction": 0.9758,
    "share_all_certified": 0.1867,
    "median_residual": 3,
    "probe_nicks_total": 72,
    "probe_nicks_matched": 16,
    "probe_cross_nick_collisions": 0,
    "probing_baseline_evil_04": 0.639501,
    "probing_recommended_evil_04": 0.31087,
    "probing_baseline_10ppd": 0.847,
    "probing_daily_cost_btc": 0.005
  },
  "pages": [
    "docs/index.html",
    "docs/mainnet-deanon.html",
    "docs/probing-attack.html"
  ]
}